flask_keystone/__init__.py
flask_keystone/anonymous.py
flask_keystone/config.py
flask_keystone/exceptions.py
flask_keystone/user.py
flask_keystone-0.2.dist-info/DESCRIPTION.rst
flask_keystone-0.2.dist-info/METADATA
flask_keystone-0.2.dist-info/RECORD
flask_keystone-0.2.dist-info/WHEEL
flask_keystone-0.2.dist-info/entry_points.txt
flask_keystone-0.2.dist-info/metadata.json
flask_keystone-0.2.dist-info/top_level.txt
