Metadata-Version: 2.0
Name: flask-keystone
Version: 0.2
Summary: This project wraps the existing keystone middleware to provide courtesy user functions within an API.
Home-page: https://github.com/Rackspace-DOT/flask_keystone
Author: Rackspace Developers for Operational Tooling
Author-email: dot@rackspace.com
License: UNKNOWN
Keywords: flask,identity,auth
Platform: any
Classifier: Intended Audience :: Developers
Classifier: Topic :: Internet :: WWW/HTTP :: Dynamic Content
Classifier: Topic :: Internet :: WWW/HTTP :: WSGI :: Middleware
Classifier: Topic :: Software Development :: Libraries :: Python Modules
Classifier: License :: OSI Approved :: Apache Software License
Classifier: Operating System :: Unix
Classifier: Operating System :: POSIX
Classifier: Programming Language :: Python :: 3.5
Classifier: Programming Language :: Python :: 3.4
Requires-Dist: Flask
Requires-Dist: keystoneauth1
Requires-Dist: keystonemiddleware
Requires-Dist: oslo.config
Requires-Dist: oslo.log
